setup.py
poseidon/__init__.py
poseidon/api.py
poseidon/client.py
poseidon/droplet.py
poseidon/ssh.py
poseidon/version.py
poseidon.egg-info/PKG-INFO
poseidon.egg-info/SOURCES.txt
poseidon.egg-info/dependency_links.txt
poseidon.egg-info/requires.txt
poseidon.egg-info/top_level.txt