Metadata-Version: 1.1
Name: poseidon
Version: 0.3.1
Summary: 
